asitop_csv_logger/__init__.py
asitop_csv_logger/asitop_csv_logger.py
asitop_csv_logger/graphing.py
asitop_csv_logger/parsers.py
asitop_csv_logger/utils.py
asitop_csv_logger-1.0.7.dist-info/METADATA
asitop_csv_logger-1.0.7.dist-info/WHEEL
asitop_csv_logger-1.0.7.dist-info/entry_points.txt
asitop_csv_logger-1.0.7.dist-info/top_level.txt
asitop_csv_logger-1.0.7.dist-info/RECORD
