Metadata-Version: 2.4
Name: asitop-csv-logger
Version: 1.0.7
Summary: CLI tool to log Apple Silicon system metrics to terminal and/or CSV
Home-page: https://github.com/Intruder2614/asitop_raw_data_csv
Author: Biswareet Panda
Author-email: biswa.gunu2003@gmail.com
License: MIT
Classifier: Programming Language :: Python :: 3
Classifier: License :: OSI Approved :: MIT License
Classifier: Operating System :: MacOS :: MacOS X
Requires-Python: >=3.7
Requires-Dist: psutil>=5.9.0
Requires-Dist: dashing>=0.1.0
Dynamic: author
Dynamic: author-email
Dynamic: classifier
Dynamic: description
Dynamic: description-content-type
Dynamic: home-page
Dynamic: license
Dynamic: requires-dist
Dynamic: requires-python
Dynamic: summary
